scalesec_gcp_workload_identity/__init__.py
scalesec_gcp_workload_identity/main.py
scalesec_gcp_workload_identity/utils.py
scalesec_gcp_workload_identity-1.0.7.dist-info/LICENSE
scalesec_gcp_workload_identity-1.0.7.dist-info/METADATA
scalesec_gcp_workload_identity-1.0.7.dist-info/WHEEL
scalesec_gcp_workload_identity-1.0.7.dist-info/top_level.txt
scalesec_gcp_workload_identity-1.0.7.dist-info/RECORD
