Metadata-Version: 2.1
Name: scalesec-gcp-workload-identity
Version: 1.0.7
Summary: This package enables AWS->GCP federation with two lines of code
Home-page: https://github.com/ScaleSec/gcp-workload-identity-federation
Author: ScaleSec
Author-email: info@scalesec.com
License: Apache License 2.0
Project-URL: Bug Tracker, https://github.com/ScaleSec/gcp-workload-identity-federation/issues
Platform: UNKNOWN
Classifier: Intended Audience :: Developers
Classifier: Natural Language :: English
Classifier: License :: OSI Approved :: Apache Software License
Classifier: Programming Language :: Python
Classifier: Programming Language :: Python :: 3
Classifier: Programming Language :: Python :: 3.6
Classifier: Programming Language :: Python :: 3.7
Classifier: Programming Language :: Python :: 3.8
Requires-Python: >= 3.6, !=3.0.*, !=3.1.*, !=3.2.*, !=3.3.*, !=3.4.*, !=3.5.*
License-File: LICENSE
Requires-Dist: boto3
Requires-Dist: requests
